mealy_t.v
/*
 * Mealy Machine Design (mealy_t)
 * This is another Mealy machine. Like mealy_d, the output depends on the internal state and the input.
 * The state flips (changes from 0 to 1 or 1 to 0) only when the input x is 1; if x is 0, the state stays put, unless reset.
 * The output is a mix (XOR) of the current state and the input, calculated instantly.
 * XOR means exclusive or: 1 if bits differ, 0 if same.
 */
module mealy_t (
    input clk,      // Clock - the timing signal that drives the machine
    input reset,    // Reset - use this to reset the state to 0 and start over
    input x,        // Input x - the bit we send to the machine
    output reg z    // Output z - the bit the machine sends back
);
    reg q;  // Internal state - keeps track of things, resets to 0

    // State update logic: Changes the state on clock ticks or reset
    always @(posedge clk or posedge reset) begin
        if (reset)
            q <= 1'b0;  // Reset: set state to 0
        else if (x)
            q <= ~q;     // If input x is 1, flip the state (0 becomes 1, 1 becomes 0)
        // If x is 0, state stays the same
    end

    // Output calculation: Computes the output right away
    always @(*) begin
        z = q ^ x;  // Output z is state XOR input x
    end
endmodule

tfsm_tb.v
`timescale 1ns/1ps

module fsm_tb;

    reg clk;
    reg reset;
    reg x;
    wire z;

    // ==============================
    // CHANGE MODULE NAME HERE
    // ==============================
    mealy_t uut (        // <- change this line if needed
        .clk(clk),
        .reset(reset),
        .x(x),
        .z(z)
    );

    // ==============================
    // CLOCK GENERATION
    // ==============================
    always #5 clk = ~clk;   // 10 ns clock period

    // ==============================
    // TEST SEQUENCE
    // ==============================
    initial begin
        $dumpfile("fsm.vcd");
        $dumpvars(0, fsm_tb);

        // Initialize
        clk = 0;
        reset = 1;
        x = 0;

        #10 reset = 0;

        // Input sequence
        #10 x = 1;
        #10 x = 0;
        #10 x = 1;
        #10 x = 1;
        #10 x = 0;
        #10 x = 1;

        #20 $finish;
    end

endmodule

dfsm.vcd
$date
	Fri Jan 09 15:35:54 2026
$end
$version
	Icarus Verilog
$end
$timescale
	1ps
$end
$scope module fsm_tb $end
$var wire 1 ! z $end
$var reg 1 " clk $end
$var reg 1 # reset $end
$var reg 1 $ x $end
$scope module uut $end
$var wire 1 " clk $end
$var wire 1 # reset $end
$var wire 1 $ x $end
$var reg 1 % q $end
$var reg 1 ! z $end
$upscope $end
$upscope $end
$enddefinitions $end
#0
$dumpvars
0%
0$
1#
0"
0!
$end
#5000
1"
#10000
0"
0#
#15000
1"
#20000
1!
0"
1$
#25000
0!
1%
1"
#30000
1!
0"
0$
#35000
1"
#40000
0!
0"
1$
#45000
1!
0%
1"
#50000
0"
#55000
0!
1%
1"
#60000
1!
0"
0$
#65000
1"
#70000
0!
0"
1$
#75000
1!
0%
1"
#80000
0"
#85000
0!
1%
1"
